Python_pyStream-0.0.2.dist-info/DESCRIPTION.rst
Python_pyStream-0.0.2.dist-info/METADATA
Python_pyStream-0.0.2.dist-info/RECORD
Python_pyStream-0.0.2.dist-info/WHEEL
Python_pyStream-0.0.2.dist-info/metadata.json
Python_pyStream-0.0.2.dist-info/top_level.txt
pystream/__init__.py
pystream/__main__.py
