Metadata-Version: 2.0
Name: Python-pyStream
Version: 0.0.2
Summary: Python Streamer
Home-page: https://github.com/hericlesme/pyStream
Author: Héricles Emanuel
Author-email: hericles.me@gmail.com
License: MIT
Platform: UNKNOWN
Classifier: Programming Language :: Python :: 2
Classifier: Programming Language :: Python :: 3
Requires-Dist: flask
Requires-Dist: pillow
Requires-Dist: pyscreenshot
